GaussianFilter/__init__.py
GaussianFilter/feature.py
GaussianFilter-0.0.4.dist-info/License.txt
GaussianFilter-0.0.4.dist-info/METADATA
GaussianFilter-0.0.4.dist-info/WHEEL
GaussianFilter-0.0.4.dist-info/top_level.txt
GaussianFilter-0.0.4.dist-info/RECORD
